kinguru_database/__init__.py
kinguru_database-0.1.0.dist-info/METADATA
kinguru_database-0.1.0.dist-info/WHEEL
kinguru_database-0.1.0.dist-info/top_level.txt
kinguru_database-0.1.0.dist-info/RECORD
