Metadata-Version: 2.1
Name: kinguru-database
Version: 0.1.0
Summary: Crud  simplificado
Author: Gleison de souza luiz
Author-email: gleisonnanet@gmail.com
